figgs/__init__.py
figgs/auth.py
figgs/figgs.py
figgs_ai-0.0.7.dist-info/METADATA
figgs_ai-0.0.7.dist-info/WHEEL
figgs_ai-0.0.7.dist-info/entry_points.txt
figgs_ai-0.0.7.dist-info/top_level.txt
figgs_ai-0.0.7.dist-info/RECORD
