Metadata-Version: 2.1
Name: figgs-ai
Version: 0.0.7
Summary: A simple figgs.ai API
Home-page: https://github.com/DeoDorqnt387/Unofficial-the-worst-figgs.ai-API.git
Author: Pandora
Author-email: yigitcankocabiyik@gmail.com
Keywords: figgs,figgs.ai,figgsai api,figgs ai
Requires-Python: >=3.9
Requires-Dist: requests
Requires-Dist: beautifulsoup4
Requires-Dist: urllib3
